{
  "post": {
    "operationId": "duplicate_table_field",
    "description": "Duplicates the table with the provided `table_id` parameter if the authorized user has access to the database's workspace.",
    "parameters": [
      {
        "in": "header",
        "name": "ClientSessionId",
        "schema": {
          "type": "string",
          "format": "uuid"
        },
        "description": "An optional header that marks the action performed by this request as having occurred in a particular client session. Then using the undo/redo endpoints with the same ClientSessionId header this action can be undone/redone."
      },
      {
        "in": "header",
        "name": "ClientUndoRedoActionGroupId",
        "schema": {
          "type": "string",
          "format": "uuid"
        },
        "description": "An optional header that marks the action performed by this request as having occurred in a particular action group.Then calling the undo/redo endpoint with the same ClientSessionId header, all the actions belonging to the same action group can be undone/redone together in a single API call."
      },
      {
        "in": "path",
        "name": "field_id",
        "schema": {
          "type": "integer"
        },
        "description": "The field to duplicate.",
        "required": true
      }
    ],
    "tags": [
      "Database table fields"
    ],
    "security": [
      {
        "UserSource JWT": []
      },
      {
        "JWT": []
      }
    ],
    "responses": {
      "202": {
        "content": {
          "application/json": {
            "schema": {
              "$ref": "../components/schemas/DuplicateFieldJobTypeResponse.json"
            }
          }
        },
        "description": ""
      },
      "400": {
        "content": {
          "application/json": {
            "schema": {
              "type": "object",
              "properties": {
                "error": {
                  "type": "string",
                  "description": "Machine readable error indicating what went wrong.",
                  "enum": [
                    "ERROR_USER_NOT_IN_GROUP",
                    "ERROR_REQUEST_BODY_VALIDATION",
                    "ERROR_MAX_JOB_COUNT_EXCEEDED"
                  ]
                },
                "detail": {
                  "oneOf": [
                    {
                      "type": "string",
                      "format": "string",
                      "description": "Human readable details about what went wrong."
                    },
                    {
                      "type": "object",
                      "format": "object",
                      "description": "Machine readable object about what went wrong."
                    }
                  ]
                }
              }
            }
          }
        },
        "description": ""
      },
      "404": {
        "content": {
          "application/json": {
            "schema": {
              "type": "object",
              "properties": {
                "error": {
                  "type": "string",
                  "description": "Machine readable error indicating what went wrong.",
                  "enum": [
                    "ERROR_FIELD_DOES_NOT_EXIST"
                  ]
                },
                "detail": {
                  "oneOf": [
                    {
                      "type": "string",
                      "format": "string",
                      "description": "Human readable details about what went wrong."
                    },
                    {
                      "type": "object",
                      "format": "object",
                      "description": "Machine readable object about what went wrong."
                    }
                  ]
                }
              }
            }
          }
        },
        "description": ""
      }
    }
  }
}